imgresizer/__init__.py
imgresizer/__main__.py
imgresizer/controller/__init__.py
imgresizer/controller/image_sizer_controller.py
imgresizer/model/__init__.py
imgresizer/model/image.py
imgresizer/view/__init__.py
imgresizer/view/cli_image_resizer.py
imgresizer-1.0.0.dist-info/LICENSE
imgresizer-1.0.0.dist-info/METADATA
imgresizer-1.0.0.dist-info/WHEEL
imgresizer-1.0.0.dist-info/entry_points.txt
imgresizer-1.0.0.dist-info/top_level.txt
imgresizer-1.0.0.dist-info/RECORD
