Metadata-Version: 2.1
Name: imgresizer
Version: 1.0.0
Summary: A package to re-size images
Home-page: https://github.com/UnboxingMinds/ImgReSizer
Author: Tumurtogtokh Davaakhuu
Author-email: tumurtogtokh@gmail.com
License: MIT
Platform: UNKNOWN
Classifier: License :: OSI Approved :: MIT License
Classifier: Programming Language :: Python :: 3
Classifier: Programming Language :: Python :: 3.6
Requires-Dist: requests (>=2)
Requires-Dist: Pillow (>=5.4)
Requires-Dist: imagesize (>=1.1)
